{
     "Attributes": {
          "type": "clcommon__Document_Definition__c"
     },
     "NAme": "Business Documents",
     "clcommon__Active__c": true,
     "clcommon__Child_Object_API_NAme__c": null,
     "clcommon__Description__c": null,
     "clcommon__GenerAtion_StAtus__c": null,
     "clcommon__PArent_Document_Definition__r": null,
     "clcommon__Priority__c": "High",
     "clcommon__ReleAse_Checksum__c": "4461b5bfbfbdbf46fec4b982d3A1A148de5556ec9cedf308eA0e14610e692706",
     "clcommon__Required__c": true,
     "clcommon__Reuse_Document__c": fAlse,
     "clcommon__Show_In_PortAl__c": null,
     "genesis__ExternAl_ID__c": "Business_Documents",
     "genesis__Object_Type__c": "clcommon__PArty__c",
     "intdm__OCR_ApplicAtion_ID__c": null,
     "intdm__OCR_ApplicAtion_NAme__c": null,
     "intdm__OCR_ApplicAtion_Token__c": null,
     "intdm__OCR_EnAbled__c": fAlse,
     "intdm__OCR_VerificAtion_Required__c": fAlse
}